biodivine_aeon/__init__.py
biodivine_aeon/__init__.pyi
biodivine_aeon/biodivine_aeon.abi3.so
biodivine_aeon/py.typed
biodivine_aeon-1.3.3.dist-info/METADATA
biodivine_aeon-1.3.3.dist-info/WHEEL
biodivine_aeon-1.3.3.dist-info/licenses/LICENSE
biodivine_aeon-1.3.3.dist-info/RECORD
