Metadata-Version: 2.4
Name: biodivine_aeon
Version: 1.3.3
Classifier: Development Status :: 4 - Beta
Classifier: Intended Audience :: Science/Research
Classifier: License :: OSI Approved :: MIT License
Classifier: Programming Language :: Rust
Classifier: Programming Language :: Python :: 3
Classifier: Programming Language :: Python :: 3.9
Classifier: Programming Language :: Python :: 3.10
Classifier: Programming Language :: Python :: 3.11
Classifier: Programming Language :: Python :: 3.12
Classifier: Programming Language :: Python :: Implementation :: CPython
Classifier: Programming Language :: Python :: Implementation :: PyPy
Classifier: Topic :: Scientific/Engineering :: Bio-Informatics
Classifier: Topic :: Scientific/Engineering :: Mathematics
License-File: LICENSE
Summary: Python bindings for the tool AEON.
Keywords: boolean-networks,systems-biology,model-checking,bdd,symbolic-computation,attractors,control
Author: sybila
License: MIT
Requires-Python: >=3.9
Project-URL: Documentation, https://biodivine.fi.muni.cz/docs/aeon-py/latest/
Project-URL: Repository, https://github.com/sybila/biodivine-aeon-py/
